[
    {
        "name": "id",
        "dbType": "id",
        "htmlType": null,
        "validations": null,
        "searchable": false,
        "fillable": false,
        "primary": true,
        "inForm": false,
        "inIndex": false,
        "inView": false
    },
    {
        "name": "name",
        "dbType": "string:nullable",
        "htmlType": "text",
        "validations": "",
        "searchable": true,
        "fillable": true,
        "primary": false,
        "inForm": true,
        "inIndex": true,
        "inView": true
    },
    {
        "name": "logo",
        "dbType": "string:nullable",
        "htmlType": "file",
        "validations": "",
        "searchable": true,
        "fillable": true,
        "primary": false,
        "inForm": true,
        "inIndex": true,
        "inView": true
    },
    {
        "name": "description",
        "dbType": "text:nullable",
        "htmlType": "textarea",
        "validations": "",
        "searchable": true,
        "fillable": true,
        "primary": false,
        "inForm": true,
        "inIndex": true,
        "inView": true
    },
    {
        "name": "email",
        "dbType": "string:nullable",
        "htmlType": "text",
        "validations": "",
        "searchable": true,
        "fillable": true,
        "primary": false,
        "inForm": true,
        "inIndex": true,
        "inView": true
    },
    {
        "name": "contact",
        "dbType": "string:nullable",
        "htmlType": "text",
        "validations": "",
        "searchable": true,
        "fillable": true,
        "primary": false,
        "inForm": true,
        "inIndex": true,
        "inView": true
    },
    {
        "name": "location",
        "dbType": "string:nullale",
        "htmlType": "text",
        "validations": "",
        "searchable": true,
        "fillable": true,
        "primary": false,
        "inForm": true,
        "inIndex": true,
        "inView": true
    },
    {
        "name": "country",
        "dbType": "string:nullable",
        "htmlType": "text",
        "validations": "",
        "searchable": true,
        "fillable": true,
        "primary": false,
        "inForm": true,
        "inIndex": true,
        "inView": true
    },
    {
        "name": "city",
        "dbType": "string:nullable",
        "htmlType": "text",
        "validations": "",
        "searchable": true,
        "fillable": true,
        "primary": false,
        "inForm": true,
        "inIndex": true,
        "inView": true
    },
    {
        "name": "created_at",
        "dbType": "timestamp",
        "htmlType": null,
        "validations": null,
        "searchable": false,
        "fillable": false,
        "primary": false,
        "inForm": false,
        "inIndex": false,
        "inView": true
    },
    {
        "name": "updated_at",
        "dbType": "timestamp",
        "htmlType": null,
        "validations": null,
        "searchable": false,
        "fillable": false,
        "primary": false,
        "inForm": false,
        "inIndex": false,
        "inView": true
    }
]